Metadata-Version: 2.1
Name: odoo-addon-stock-account-quantity-history-location
Version: 15.0.1.0.0.4
Summary: Glue module between Stock Account and Stock Quantity History Location modules
Home-page: https://github.com/OCA/stock-logistics-reporting
Author: Eficent, Odoo Community Association (OCA)
Author-email: support@odoo-community.org
License: AGPL-3
Platform: UNKNOWN
Classifier: Programming Language :: Python
Classifier: Framework :: Odoo
Classifier: Framework :: Odoo :: 15.0
Classifier: License :: OSI Approved :: GNU Affero General Public License v3
Requires-Python: >=3.8
Requires-Dist: odoo-addon-stock-quantity-history-location <15.1dev,>=15.0dev
Requires-Dist: odoo <15.1dev,>=15.0a
